redis/__init__.py
redis/_compat.py
redis/client.py
redis/connection.py
redis/exceptions.py
redis/lock.py
redis/sentinel.py
redis/utils.py
yb-redis/__init__.py
yb-redis/_compat.py
yb-redis/client.py
yb-redis/connection.py
yb-redis/exceptions.py
yb-redis/lock.py
yb-redis/sentinel.py
yb-redis/utils.py
yedis/__init__.py
yedis/_compat.py
yedis/client.py
yedis/connection.py
yedis/exceptions.py
yedis/lock.py
yedis/sentinel.py
yedis/utils.py
yedis-2.10.6.0.dist-info/LICENSE
yedis-2.10.6.0.dist-info/METADATA
yedis-2.10.6.0.dist-info/WHEEL
yedis-2.10.6.0.dist-info/top_level.txt
yedis-2.10.6.0.dist-info/RECORD
