Metadata-Version: 2.1
Name: yedis
Version: 2.10.6.0
Summary: Python client for Redis key-value store, extended to support additional features from YugaByteDB
Home-page: https://github.com/YugaByte/yb-redis-py
Author: Andy McCurdy
Author-email: sedrik@gmail.com
Maintainer: Amitanand Aiyer
Maintainer-email: amitanand@yugabyte.com
License: MIT
Keywords: YugaByte,YugaByteDB,Yedis,Redis,key-value store
Platform: UNKNOWN
Classifier: Development Status :: 5 - Production/Stable
Classifier: Environment :: Console
Classifier: Intended Audience :: Developers
Classifier: License :: OSI Approved :: MIT License
Classifier: Operating System :: OS Independent
Classifier: Programming Language :: Python
Classifier: Programming Language :: Python :: 2
Classifier: Programming Language :: Python :: 2.6
Classifier: Programming Language :: Python :: 2.7
Classifier: Programming Language :: Python :: 3
Classifier: Programming Language :: Python :: 3.3
Classifier: Programming Language :: Python :: 3.4
Classifier: Programming Language :: Python :: 3.5
Classifier: Programming Language :: Python :: 3.6
Provides-Extra: hiredis
Requires-Dist: hiredis (>=0.1.3); extra == 'hiredis'
